healpy-1.17.3.dist-info/COPYING
healpy-1.17.3.dist-info/WHEEL
healpy-1.17.3.dist-info/top_level.txt
healpy-1.17.3.dist-info/RECORD
healpy-1.17.3.dist-info/METADATA
healpy-1.17.3.data/scripts/healpy_get_wmap_maps.sh
healpy/fitsfunc.py
healpy/zoomtool.py
healpy/_masktools.cpython-312-aarch64-linux-gnu.so
healpy/__init__.py
healpy/cookbook.py
healpy/visufunc.py
healpy/_line_integral_convolution.cpython-312-aarch64-linux-gnu.so
healpy/rotator.py
healpy/conftest.py
healpy/projaxes.py
healpy/sphtfunc.py
healpy/_healpy_sph_transform_lib.cpython-312-aarch64-linux-gnu.so
healpy/_query_disc.cpython-312-aarch64-linux-gnu.so
healpy/version.py
healpy/_hotspots.cpython-312-aarch64-linux-gnu.so
healpy/projector.py
healpy/_sphtools.cpython-312-aarch64-linux-gnu.so
healpy/_healpy_pixel_lib.cpython-312-aarch64-linux-gnu.so
healpy/pixelfunc.py
healpy/newvisufunc.py
healpy/_pixelfunc.cpython-312-aarch64-linux-gnu.so
healpy/data/weight_ring_n00512.fits
healpy/data/weight_ring_n00008.fits
healpy/data/weight_ring_n00064.fits
healpy/data/wmap_cmap.dat
healpy/data/weight_ring_n00032.fits
healpy/data/weight_ring_n00004.fits
healpy/data/totcls.dat
healpy/data/pixel_window_n0256.fits
healpy/data/planck_log_cmap.dat
healpy/data/pixel_window_n0128.fits
healpy/data/pixel_window_n1024.fits
healpy/data/weight_ring_n00128.fits
healpy/data/weight_ring_n00002.fits
healpy/data/planck_cmap.dat
healpy/data/pixel_window_n2048.fits
healpy/data/weight_ring_n04096.fits
healpy/data/pixel_window_n0512.fits
healpy/data/pixel_window_n8192.fits
healpy/data/pixel_window_n4096.fits
healpy/data/pixel_window_n0032.fits
healpy/data/weight_ring_n01024.fits
healpy/data/weight_ring_n00256.fits
healpy/data/pixel_window_n0016.fits
healpy/data/pixel_window_n0008.fits
healpy/data/weight_ring_n08192.fits
healpy/data/pixel_window_n0064.fits
healpy/data/weight_ring_n00016.fits
healpy/data/weight_ring_n02048.fits
healpy/data/pixel_window_n0002.fits
healpy/data/pixel_window_n0004.fits
healpy/utils/__init__.py
healpy/utils/deprecation.py
healpy.libs/libgomp-d22c30c5.so.1.0.0
healpy.libs/libsharp-534a9048.so.2.0.2
