Metadata-Version: 2.1
Name: healpy
Version: 1.17.3
Summary: Healpix tools package for Python
Author: A. Zonca
Author-email: "C. Rosset" <cyrille.rosset@apc.univ-paris-diderot.fr>
License: GPL-2.0-only
Project-URL: homepage, http://github.com/healpy
Classifier: Development Status :: 5 - Production/Stable
Classifier: Environment :: Console
Classifier: Intended Audience :: Science/Research
Classifier: License :: OSI Approved :: GNU General Public License v2 or later (GPLv2+)
Classifier: Operating System :: POSIX
Classifier: Programming Language :: C++
Classifier: Programming Language :: Python :: 3.9
Classifier: Programming Language :: Python :: 3.10
Classifier: Programming Language :: Python :: 3.11
Classifier: Programming Language :: Python :: 3.12
Classifier: Topic :: Scientific/Engineering :: Astronomy
Classifier: Topic :: Scientific/Engineering :: Visualization
Requires-Python: >=3.9
License-File: COPYING
Requires-Dist: numpy>=1.19
Requires-Dist: astropy
Provides-Extra: all
Requires-Dist: matplotlib; extra == "all"
Requires-Dist: scipy; extra == "all"
Provides-Extra: test
Requires-Dist: pytest; extra == "test"
Requires-Dist: pytest-astropy-header; extra == "test"
Requires-Dist: pytest-cython; extra == "test"
Requires-Dist: pytest-doctestplus; extra == "test"
Requires-Dist: requests; extra == "test"
Requires-Dist: matplotlib; extra == "test"
Requires-Dist: scipy; extra == "test"
